func_az/__init__.py
func_az/jobs.py
func_az/safe.py
func_az-0.1.9.dist-info/METADATA
func_az-0.1.9.dist-info/WHEEL
func_az-0.1.9.dist-info/top_level.txt
func_az-0.1.9.dist-info/RECORD
