Metadata-Version: 2.1
Name: func-az
Version: 0.1.9
Summary: Tools for Azure Functions
Author-email: Marcel Claramunt <marcel@moveread.com>
Project-URL: repo, https://github.com/moveread/func-az.git
Requires-Python: >=3.10
Requires-Dist: azure-functions
Requires-Dist: dslog
Requires-Dist: haskellian
